polars_streaming/__init__.py
polars_streaming/core.py
polars_streaming/exceptions.py
polars_streaming/readwriter.py
polars_streaming/processors/__init__.py
polars_streaming/processors/fileProcessor.py
polars_streaming/processors/kafkaProcessor.py
polars_streaming/processors/socketProcessor.py
polars_streaming/processors/utils.py
polars_streaming/sinks/__init__.py
polars_streaming/sinks/esWriter.py
polars_streaming/sinks/mongoWriter.py
polars_streaming/sinks/sink_utils.py
polars_streaming-0.3.0.dist-info/LICENSE
polars_streaming-0.3.0.dist-info/METADATA
polars_streaming-0.3.0.dist-info/WHEEL
polars_streaming-0.3.0.dist-info/top_level.txt
polars_streaming-0.3.0.dist-info/RECORD
