Metadata-Version: 2.1
Name: polars-streaming
Version: 0.3.0
Summary: Stream Processing Library using Polars
Author-email: Vinish M <vinishuchiha@gmail.com>
License: Apache License
Project-URL: Homepage, https://github.com/VinishUchiha/polars-streaming
Keywords: polars,streaming,polars streaming,stream processing
Classifier: License :: OSI Approved :: Apache Software License
Classifier: Programming Language :: Python
Classifier: Programming Language :: Python :: 3
Requires-Python: >=3.7
License-File: LICENSE
Requires-Dist: polars
Requires-Dist: watchdog
Requires-Dist: schedule
Requires-Dist: tomli ; python_version < "3.11"
Provides-Extra: dev
Requires-Dist: black ; extra == 'dev'
Requires-Dist: bumpver ; extra == 'dev'
Requires-Dist: isort ; extra == 'dev'
Requires-Dist: pip-tools ; extra == 'dev'
Requires-Dist: pytest ; extra == 'dev'
Provides-Extra: kafka
Requires-Dist: confluent-kafka ; extra == 'kafka'
